Metadata-Version: 2.1
Name: django-guid-folked
Version: 3.3.2
Summary: Middleware that enables single request-response cycle tracing by injecting a unique ID into project logs
Home-page: https://github.com/snok/django-guid
License: MIT
Keywords: asgi,async,async support,correlation,correlation-id,django,guid,log id,logging,logging id,middleware,request,request id,request-id,uuid,web,sentry,celery
Author: Jonas Krüger Svensson
Author-email: jonas-ks@hotmail.com
Maintainer: Sondre Lillebø Gundersen
Maintainer-email: sondrelg@live.no
Requires-Python: >=3.7,<4.0
Classifier: Development Status :: 5 - Production/Stable
Classifier: Environment :: Web Environment
Classifier: Framework :: Django
Classifier: Framework :: Django :: 3.0
Classifier: Framework :: Django :: 3.1
Classifier: Framework :: Django :: 3.2
Classifier: Framework :: Django :: 4.0
Classifier: Framework :: Django :: 4.1
Classifier: Intended Audience :: Developers
Classifier: License :: OSI Approved :: BSD License
Classifier: License :: OSI Approved :: MIT License
Classifier: Operating System :: OS Independent
Classifier: Programming Language :: Python
Classifier: Programming Language :: Python :: 3
Classifier: Programming Language :: Python :: 3.7
Classifier: Programming Language :: Python :: 3.8
Classifier: Programming Language :: Python :: 3.9
Classifier: Programming Language :: Python :: 3.10
Classifier: Programming Language :: Python :: 3.11
Classifier: Topic :: Internet :: WWW/HTTP
Classifier: Topic :: Internet :: WWW/HTTP :: Dynamic Content
Classifier: Topic :: Internet :: WWW/HTTP :: WSGI
Classifier: Topic :: Software Development
Classifier: Topic :: Software Development :: Libraries
Classifier: Topic :: Software Development :: Libraries :: Application Frameworks
Classifier: Topic :: Software Development :: Libraries :: Python Modules
Requires-Dist: django (>=3.1.1,<4.0.0) ; python_version < "3.8"
Requires-Dist: django (>=3.1.1,<5.0) ; python_version >= "3.8"
Project-URL: Documentation, https://django-guid.readthedocs.io/en/latest
Project-URL: Repository, https://github.com/snok/django-guid
Project-URL: Release notes, https://github.com/snok/django-guid/releases
